policyguard/__init__.py
policyguard/__version__.py
policyguard/cli.py
policyguard/hooks.py
policyguard/rules.py
policyguard/scanner.py
policyguard/core/__init__.py
policyguard/core/engine.py
policyguard/core/transformers.py
policyguard/integrations/__init__.py
policyguard/rules/advanced_rules.py
policyguard-real/setup.py
policyguard-real/policyguard/__init__.py
policyguard-real/policyguard/cli.py
policyguard-real/policyguard/scanner.py
policyguard_paolovella-0.1.0.dist-info/licenses/LICENSE
policyguard_paolovella-0.1.0.dist-info/METADATA
policyguard_paolovella-0.1.0.dist-info/WHEEL
policyguard_paolovella-0.1.0.dist-info/entry_points.txt
policyguard_paolovella-0.1.0.dist-info/top_level.txt
policyguard_paolovella-0.1.0.dist-info/RECORD
