Metadata-Version: 2.4
Name: policyguard-paolovella
Version: 0.1.0
Summary: Pre-commit hook for detecting security issues in AI-generated code
Author-email: Paolo vella <paolovella1993@gmail.com>
License: MIT
Project-URL: Homepage, https://github.com/yourusername/policyguard
Project-URL: Documentation, https://policyguard.readthedocs.io
Project-URL: Repository, https://github.com/yourusername/policyguard
Project-URL: Issues, https://github.com/yourusername/policyguard/issues
Keywords: security,linter,pre-commit,ai,copilot,code-quality
Classifier: Development Status :: 4 - Beta
Classifier: Environment :: Console
Classifier: Intended Audience :: Developers
Classifier: License :: OSI Approved :: MIT License
Classifier: Operating System :: OS Independent
Classifier: Programming Language :: Python :: 3
Classifier: Programming Language :: Python :: 3.7
Classifier: Programming Language :: Python :: 3.8
Classifier: Programming Language :: Python :: 3.9
Classifier: Programming Language :: Python :: 3.10
Classifier: Programming Language :: Python :: 3.11
Classifier: Topic :: Security
Classifier: Topic :: Software Development :: Quality Assurance
Classifier: Topic :: Software Development :: Testing
Requires-Python: >=3.7
License-File: LICENSE
Requires-Dist: click>=8.0
Requires-Dist: colorama>=0.4.4; platform_system == "Windows"
Provides-Extra: dev
Requires-Dist: pytest>=7.0; extra == "dev"
Requires-Dist: pytest-cov>=4.0; extra == "dev"
Requires-Dist: black>=22.0; extra == "dev"
Requires-Dist: mypy>=0.990; extra == "dev"
Requires-Dist: ruff>=0.0.261; extra == "dev"
Dynamic: license-file
